latestversions/LatestVersions.py
latestversions/__init__.py
latestversions/_version.py
latestversions/resources/__init__.py
latestversions/resources/loggingConfiguration.json
latestversions-1.3.0.dist-info/licenses/LICENSE
latestversions-1.3.0.dist-info/METADATA
latestversions-1.3.0.dist-info/WHEEL
latestversions-1.3.0.dist-info/entry_points.txt
latestversions-1.3.0.dist-info/top_level.txt
latestversions-1.3.0.dist-info/RECORD
