Metadata-Version: 2.4
Name: latestversions
Version: 1.3.0
Summary: Reports the latest versions of PyPi packages
Author-email: "Humberto A. Sanchez II" <Humbert.A.Sanchez.II@gmail.com>
Maintainer-email: "Humberto A. Sanchez II" <Humbert.A.Sanchez.II@gmail.com>
Project-URL: Repository, https://github.com/hasii2011/latestversions
Keywords: requirements,versions,python
Classifier: Programming Language :: Python
Classifier: Intended Audience :: Developers
Classifier: Operating System :: MacOS :: MacOS X
Classifier: Topic :: Software Development :: Libraries :: Python Modules
License-File: LICENSE
Requires-Dist: click>=8.2.1
Requires-Dist: codeallybasic>=1.8.0
Provides-Extra: test
Requires-Dist: mypy==1.16.1; extra == "test"
Requires-Dist: mypy-extensions==1.1.0; extra == "test"
Requires-Dist: types-Deprecated==1.2.9.20240311; extra == "test"
Requires-Dist: html-testRunner~=1.2.1; extra == "test"
Requires-Dist: codeallybasic==1.10.4; extra == "test"
Provides-Extra: deploy
Requires-Dist: wheel==0.45.1; extra == "deploy"
Requires-Dist: setuptools==75.7.0; extra == "deploy"
Requires-Dist: twine==6.0.1; extra == "deploy"
Requires-Dist: build==1.2.2.post1; extra == "deploy"
Requires-Dist: pkginfo==1.12.1.2; extra == "deploy"
Dynamic: license-file
